{
  "manifest": {
    "0": {
      "name": "Status Hub",
      "slug": "status",
      "path": "/status/",
      "icon": "layout-list",
      "description": "Intelligence records, observations, and infrastructure logs.",
      "tags": ["infra", "status", "logs"],
      "keyed": false,
      "status": "live"
    },
    "1": {
      "name": "Context Memory",
      "slug": "status",
      "path": "/status/logs/",
      "icon": "circle",
      "description": "Memory, Context and Logs for the codebase",
      "tags": ["infra", "memory", "logs"],
      "keyed": false,
      "status": "live"
    }
  }
}
